iconsdk/__init__.py
iconsdk/async_service.py
iconsdk/exception.py
iconsdk/icon_service.py
iconsdk/monitor.py
iconsdk/signed_transaction.py
iconsdk/builder/__init__.py
iconsdk/builder/call_builder.py
iconsdk/builder/transaction_builder.py
iconsdk/libs/__init__.py
iconsdk/libs/in_memory_zip.py
iconsdk/libs/serializer.py
iconsdk/libs/signer.py
iconsdk/providers/__init__.py
iconsdk/providers/aiohttp_provider.py
iconsdk/providers/async_provider.py
iconsdk/providers/http_provider.py
iconsdk/providers/provider.py
iconsdk/providers/url_map.py
iconsdk/utils/__init__.py
iconsdk/utils/convert_type.py
iconsdk/utils/converter.py
iconsdk/utils/hexadecimal.py
iconsdk/utils/templates.py
iconsdk/utils/type.py
iconsdk/utils/validation.py
iconsdk/utils/typing/__init__.py
iconsdk/utils/typing/conversion.py
iconsdk/wallet/__init__.py
iconsdk/wallet/wallet.py
iconsdk-2.6.0.dist-info/METADATA
iconsdk-2.6.0.dist-info/WHEEL
iconsdk-2.6.0.dist-info/RECORD
