Metadata-Version: 2.4
Name: iconsdk
Version: 2.6.0
Summary: ICON SDK for Python is a collection of libraries that allow you to interact with local or remote ICON nodes using HTTP connections.
Project-URL: Repository, https://github.com/icon-project/icon-sdk-python
Project-URL: Releases, https://github.com/icon-project/icon-sdk-python/releases
Author-email: ICON Foundation <foo@icon.foundation>
License: Apache License 2.0
Classifier: Development Status :: 5 - Production/Stable
Classifier: Intended Audience :: Developers
Classifier: Intended Audience :: System Administrators
Classifier: License :: OSI Approved :: Apache Software License
Classifier: Operating System :: OS Independent
Classifier: Programming Language :: Python
Classifier: Programming Language :: Python :: 3 :: Only
Classifier: Programming Language :: Python :: 3.9
Classifier: Programming Language :: Python :: 3.10
Classifier: Programming Language :: Python :: 3.11
Classifier: Programming Language :: Python :: 3.12
Classifier: Programming Language :: Python :: 3.13
Requires-Python: >=3.9
Requires-Dist: aiohttp>=3.12.13
Requires-Dist: coincurve>=21.0.0
Requires-Dist: eth-keyfile>=0.9.1
Requires-Dist: multimethod>=2.0
Requires-Dist: requests>=2.32.4
Requires-Dist: websocket-client>=1.8.0
